{"name":"openMoodleProjectTest","id":"com.udemy.automation.test.OpenMoodleProject:openMoodleProjectTest","testCaseName":"com.udemy.automation.test.OpenMoodleProject","testSteps":[{"number":1,"description":"Enrique open browser moodle","duration":3786,"startTime":"2022-11-01T19:17:33.967-05:00[America/Bogota]","result":"SUCCESS","precondition":false,"level":0,"children":[{"number":2,"description":"Enrique opens the http://190.104.11.22:8082/moodle/login/index.php","duration":3764,"startTime":"2022-11-01T19:17:33.985-05:00[America/Bogota]","result":"SUCCESS","precondition":false,"level":1}]},{"number":3,"description":"Then label remember exists should be \u0027Recordar nombre de usuario\u0027","duration":38,"startTime":"2022-11-01T19:17:37.870-05:00[America/Bogota]","result":"SUCCESS","precondition":false,"level":0},{"number":4,"description":"Then input username exists","duration":50,"startTime":"2022-11-01T19:17:37.910-05:00[America/Bogota]","result":"SUCCESS","precondition":false,"level":0},{"number":5,"description":"Then Acceder","duration":63,"startTime":"2022-11-01T19:17:37.961-05:00[America/Bogota]","result":"SUCCESS","precondition":false,"level":0},{"number":6,"description":"Then image logo moodle exists","duration":57,"startTime":"2022-11-01T19:17:38.025-05:00[America/Bogota]","result":"SUCCESS","precondition":false,"level":0},{"number":7,"description":"Then input password exists","duration":30,"startTime":"2022-11-01T19:17:38.083-05:00[America/Bogota]","result":"SUCCESS","precondition":false,"level":0},{"number":8,"description":"Enrique insert credentials moodle","duration":2598,"startTime":"2022-11-01T19:17:38.114-05:00[America/Bogota]","result":"SUCCESS","precondition":false,"level":0,"children":[{"number":9,"description":"Enrique enters \u0027hcalani\u0027 then hits [TAB] into #username","duration":278,"startTime":"2022-11-01T19:17:38.146-05:00[America/Bogota]","result":"SUCCESS","precondition":false,"level":1},{"number":10,"description":"Enrique enters \u0027(kC4VR\u003c2\u0027 into #password","duration":162,"startTime":"2022-11-01T19:17:38.425-05:00[America/Bogota]","result":"SUCCESS","precondition":false,"level":1},{"number":11,"description":"Enrique clicks on #loginbtn","duration":2122,"startTime":"2022-11-01T19:17:38.589-05:00[America/Bogota]","result":"SUCCESS","precondition":false,"level":1}]}],"userStory":{"id":"com.udemy.automation.test.OpenMoodleProject","storyName":"Open moodle project","storyClassName":"com.udemy.automation.test.OpenMoodleProject","path":"com.udemy.automation.test","type":"story"},"featureTag":{"name":"Test/Open moodle project","type":"story","displayName":"Test/Open moodle project"},"title":"Open moodle project test","tags":[{"name":"","type":"feature","displayName":""},{"name":"Test/Open moodle project","type":"story","displayName":"Test/Open moodle project"}],"startTime":"2022-11-01T19:17:33.511-05:00[America/Bogota]","duration":7204,"projectKey":"","isManualTestingUpToDate":false,"manual":false,"testSource":"JUnit","actors":[{"name":"Enrique","can":["browse the web"]}],"result":"SUCCESS"}